EPICS_CA/CA.py
EPICS_CA/CAServer.py
EPICS_CA/__init__.py
EPICS_CA/_version.py
EPICS_CA/tests/__init__.py
EPICS_CA/tests/conftest.py
EPICS_CA/tests/test_CA.py
EPICS_CA/tests/test_caproto_interoperability.py
EPICS_CA/tests/test_examples.py
EPICS_CA/tests/test_str.py
EPICS_CA-3.4.9.dist-info/AUTHORS.rst
EPICS_CA-3.4.9.dist-info/LICENSE
EPICS_CA-3.4.9.dist-info/METADATA
EPICS_CA-3.4.9.dist-info/WHEEL
EPICS_CA-3.4.9.dist-info/entry_points.txt
EPICS_CA-3.4.9.dist-info/top_level.txt
EPICS_CA-3.4.9.dist-info/RECORD
