Metadata-Version: 2.1
Name: EPICS-CA
Version: 3.4.9
Summary: EPICS Channel Access Protocol Python Module
Home-page: https://github.com/friedrich-schotte/EPICS_CA
Author: Friedrich Schotte
Author-email: friedrich.schotte@gmail.com
License: BSD (3-clause)
Platform: UNKNOWN
Classifier: Development Status :: 2 - Pre-Alpha
Classifier: Natural Language :: English
Classifier: Programming Language :: Python :: 3
Requires-Python: >=2.7
Requires-Dist: numpy
Requires-Dist: psutil
Requires-Dist: pip
